{
    "products" : 
    [
        {
            "id": 1,
            "name" : "Creek Classic",
            "image-path" : "/produktbilleder/cd_afspillere/",
            "price" : "200",
            "category" : 1,
            "producer" : 1
        },
        {
            "id": 2,
            "name" : "Creek Destiny",
            "image-path" : "/produktbilleder/cd_afspillere/",
            "price" : "201",
            "category" : 1,
            "producer" : 1
        },
        {
            "id": 3,
            "name" : "Creek Evolution",
            "image-path" : "/produktbilleder/cd_afspillere/",
            "price" : "202",
            "category" : 1,
            "producer" : 1
        },
        {
            "id": 4,
            "name" : "Creek Expo",
            "image-path" : "/produktbilleder/cd_afspillere/",
            "price" : "203",
            "category" : 1,
            "producer" : 1
        },
        {
            "id": 5,
            "name" : "Creek Classic",
            "image-path" : "/produktbilleder/dvdafspillere/",
            "price" : "204",
            "category" : 2,
            "producer" : 1
        },
        {
            "id": 6,
            "name" : "Creek Exposure",
            "image-path" : "/produktbilleder/dvdafspillere/",
            "price" : "205",
            "category" : 2,
            "producer" : 1
        },
        {
            "id": 7,
            "name" : "Parasound 200",
            "image-path" : "/produktbilleder/dvdafspillere/",
            "price" : "206",
            "category" : 2,
            "producer" : 2
        },
        {
            "id": 8,
            "name" : "Parasound Halo d3",
            "image-path" : "/produktbilleder/dvdafspillere/",
            "price" : "207",
            "category" : 2,
            "producer" : 2
        },
        {
            "id": 9,
            "name" : "Manley Mahi",
            "image-path" : "/produktbilleder/effektforstaerkere/",
            "price" : "208",
            "category" : 3,
            "producer" : 3
        },
        {
            "id": 10,
            "name" : "Manley Neoclassic",
            "image-path" : "/produktbilleder/effektforstaerkere/",
            "price" : "208",
            "category" : 3,
            "producer" : 3
        },
        {
            "id": 11,
            "name" : "Manley Snapper",
            "image-path" : "/produktbilleder/effektforstaerkere/",
            "price" : "209",
            "category" : 3,
            "producer" : 3
        },
        {
            "id": 12,
            "name" : "Parasound Halo A23",
            "image-path" : "/produktbilleder/effektforstaerkere/",
            "price" : "210",
            "category" : 3,
            "producer" : 2
        },
        {
            "id": 13,
            "name" : "Creek OBH Passive",
            "image-path" : "/produktbilleder/forforstaerkere/",
            "price" : "211",
            "category" : 4,
            "producer" : 1
        },
        {
            "id": 14,
            "name" : "Parasound classic 7100",
            "image-path" : "/produktbilleder/forforstaerkere/",
            "price" : "212",
            "category" : 4,
            "producer" : 2
        },
        {
            "id": 15,
            "name" : "Parasound Halo p3",
            "image-path" : "/produktbilleder/forforstaerkere/",
            "price" : "213",
            "category" : 4,
            "producer" : 2
        },
        {
            "id": 16,
            "name" : "Project Prebox",
            "image-path" : "/produktbilleder/forforstaerkere/",
            "price" : "214",
            "category" : 4,
            "producer" : 4
        },
        {
            "id": 17,
            "name" : "Boesendorfer Wall",
            "image-path" : "/produktbilleder/hojtalere/",
            "price" : "215",
            "category" : 5,
            "producer" : 5
        },
        {
            "id": 18,
            "name" : "Epos M5",
            "image-path" : "/produktbilleder/hojtalere/",
            "price" : "216",
            "category" : 5,
            "producer" : 6
        },
        {
            "id": 19,
            "name" : "Harbeth hl7",
            "image-path" : "/produktbilleder/hojtalere/",
            "price" : "217",
            "category" : 5,
            "producer" : 7
        },
        {
            "id": 20,
            "name" : "Harbeth Monitor",
            "image-path" : "/produktbilleder/hojtalere/",
            "price" : "218",
            "category" : 5,
            "producer" : 7
        },
        {
            "id": 21,
            "name" : "Harbeth P3",
            "image-path" : "/produktbilleder/hojtalere/",
            "price" : "219",
            "category" : 5,
            "producer" : 7
        },
        {
            "id": 22,
            "name" : "Creek a50I",
            "image-path" : "/produktbilleder/int_forstaerkere/",
            "price" : "220",
            "category" : 6,
            "producer" : 1
        },
        {
            "id": 23,
            "name" : "Creek Classic 5350",
            "image-path" : "/produktbilleder/int_forstaerkere/",
            "price" : "221",
            "category" : 6,
            "producer" : 1
        },
        {
            "id": 24,
            "name" : "Creek Destiny Amp",
            "image-path" : "/produktbilleder/int_forstaerkere/",
            "price" : "222",
            "category" : 6,
            "producer" : 1
        },
        {
            "id": 25,
            "name" : "Manley Snapper Amp",
            "image-path" : "/produktbilleder/int_forstaerkere/",
            "price" : "223",
            "category" : 6,
            "producer" : 3
        },
        {
            "id": 26,
            "name" : "Manley Stingray Amp",
            "image-path" : "/produktbilleder/int_forstaerkere/",
            "price" : "224",
            "category" : 6,
            "producer" : 3
        },
        {
            "id": 27,
            "name" : "Project Debut 3 blue",
            "image-path" : "/produktbilleder/pladespillere/",
            "price" : "225",
            "category" : 7,
            "producer" : 4
        },
        {
            "id": 28,
            "name" : "Project Debut 3 red",
            "image-path" : "/produktbilleder/pladespillere/",
            "price" : "226",
            "category" : 7,
            "producer" : 4
        },
        {
            "id": 29,
            "name" : "Project Debut 3 yellow",
            "image-path" : "/produktbilleder/pladespillere/",
            "price" : "227",
            "category" : 7,
            "producer" : 4
        },
        {
            "id": 30,
            "name" : "Project RPM 5",
            "image-path" : "/produktbilleder/pladespillere/",
            "price" : "228",
            "category" : 7,
            "producer" : 4
        },
        {
            "id": 31,
            "name" : "Project RPM 10",
            "image-path" : "/produktbilleder/pladespillere/",
            "price" : "229",
            "category" : 7,
            "producer" : 4
        },
        {
            "id": 32,
            "name" : "Jolida JD102",
            "image-path" : "/produktbilleder/roer_forstaerkere/",
            "price" : "230",
            "category" : 8,
            "producer" : 8
        },
        {
            "id": 33,
            "name" : "Jolida JD202",
            "image-path" : "/produktbilleder/roer_forstaerkere/",
            "price" : "231",
            "category" : 8,
            "producer" : 8
        },
        {
            "id": 34,
            "name" : "Jolida JD300",
            "image-path" : "/produktbilleder/roer_forstaerkere/",
            "price" : "232",
            "category" : 8,
            "producer" : 8
        },
        {
            "id": 35,
            "name" : "Jolida JD302",
            "image-path" : "/produktbilleder/roer_forstaerkere/",
            "price" : "233",
            "category" : 8,
            "producer" : 8
        },
        {
            "id": 36,
            "name" : "Jolida JD502",
            "image-path" : "/produktbilleder/roer_forstaerkere/",
            "price" : "234",
            "category" : 8,
            "producer" : 8
        }

    ]
}
